leanpub/__init__.py
leanpub/__main__.py
leanpub/shellcommandtrick.py
leanpub/watcher.py
leanpub-0.2.0.dist-info/METADATA
leanpub-0.2.0.dist-info/RECORD
leanpub-0.2.0.dist-info/WHEEL
leanpub-0.2.0.dist-info/entry_points.txt
leanpub-0.2.0.dist-info/top_level.txt
