Metadata-Version: 2.1
Name: leanpub
Version: 0.2.0
Summary: Build leanpub books locally. Watch files and build a new pdf each time they change.
Home-page: https://github.com/hayd/leanpub
Author: Andy Hayden
Author-email: andyhayden1@gmail.com
License: MIT License
Keywords: automation,pdf,format
Platform: UNKNOWN
Classifier: Development Status :: 4 - Beta
Classifier: Environment :: Console
Classifier: Intended Audience :: Developers
Classifier: License :: OSI Approved :: MIT License
Classifier: Operating System :: OS Independent
Classifier: Programming Language :: Python
Classifier: Programming Language :: Python :: 2
Classifier: Programming Language :: Python :: 2.6
Classifier: Programming Language :: Python :: 2.7
Classifier: Programming Language :: Python :: 3
Classifier: Programming Language :: Python :: 3.2
Classifier: Programming Language :: Python :: 3.3
Classifier: Programming Language :: Python :: 3.4
Classifier: Topic :: Software Development :: Libraries :: Python Modules
Requires-Dist: argh
Requires-Dist: watchdog
